MANIFEST.in
requirements.txt
setup.cfg
setup.py
dervisher/__init__.py
dervisher/dervisher.py
dervisher/event.py
dervisher/post.py
dervisher/shard.py
dervisher/stream.py
dervisher/whirling.py
dervisher/words.py
dervisher.egg-info/PKG-INFO
dervisher.egg-info/SOURCES.txt
dervisher.egg-info/dependency_links.txt
dervisher.egg-info/entry_points.txt
dervisher.egg-info/requires.txt
dervisher.egg-info/top_level.txt
samples/adjectives
samples/adverbs
samples/nouns
samples/verbs