Metadata-Version: 1.0
Name: dervisher
Version: 0.0.9
Summary: Demonstrates use of AWS kinesis and dynamodb for application events.
Home-page: http://packages.python.org/dervisher
Author: Luke Samaha
Author-email: lwsamaha@gmail.com
License: BSD
Keywords: aws kinesis dynamodb event
Platform: UNKNOWN
